fluxprint/__init__.py
fluxprint/commons.py
fluxprint/core.py
fluxprint/exceptions.py
fluxprint/io.py
fluxprint/micrometeorology.py
fluxprint/template.py
fluxprint/utils.py
fluxprint/version.py
fluxprint/model/Hsieh_et_al_2000.py
fluxprint/model/Kljun_et_al_2015.py
fluxprint/model/Kormann_and_Meixner_2001.py
fluxprint/model/__init__.py
fluxprint/model/Kljun_et_al_2015_original/__init__.py
fluxprint/model/Kljun_et_al_2015_original/calc_footprint_FFP.py
fluxprint/model/Kljun_et_al_2015_original/calc_footprint_FFP_climatology.py
fluxprintdev/__init__.py
fluxprintdev/commons.py
fluxprintdev/core.py
fluxprintdev/exceptions.py
fluxprintdev/io.py
fluxprintdev/template.py
fluxprintdev/utils.py
fluxprintdev/version.py
fluxprintdev/model/Hsieh_et_al_2000.py
fluxprintdev/model/Kljun_et_al_2015.py
fluxprintdev/model/Kormann_and_Meixner_2001.py
fluxprintdev/model/__init__.py
fluxprintdev/model/Kljun_et_al_2015_original/__init__.py
fluxprintdev/model/Kljun_et_al_2015_original/calc_footprint_FFP.py
fluxprintdev/model/Kljun_et_al_2015_original/calc_footprint_FFP_climatology.py
footprint_toolkit/__init__.py
footprint_toolkit/core.py
footprint_toolkit/io.py
footprint_toolkit/utils.py
footprint_toolkit/version.py
footprint_toolkit/ext_libs/__init__.py
footprint_toolkit/model/__init__.py
footprint_toolkit/model/ffp_kljun2015.py
fluxprint-0.0.4.dist-info/LICENSE
fluxprint-0.0.4.dist-info/METADATA
fluxprint-0.0.4.dist-info/WHEEL
fluxprint-0.0.4.dist-info/top_level.txt
fluxprint-0.0.4.dist-info/RECORD
